{"2013":"Kommuner pr. 1\/1-2007","1012":"Folkeskoler","1013":"Friskoler og private grundskoler","1015":"Specialskoler for b\u00f8rn","1063":"Studenterkurser","1061":"Gymnasier og HF-kurser","1062":"Private gymnasier og HF-kurser","1051":"Specialskoler for voksne","1026":"Uddannelsesinstitutioner for unge med s\u00e6rlige behov","1052":"Sprogcentre","2021":"Centre for P\u00e6dagogisk og psykologisk r\u00e5dgivning","2023":"Studievalg-centre","2024":"Ungdommens Uddannelsesvejledning","2031":"Diverse adresser","1014":"Kommunale ungdomsskoler og ungdomskostskoler","1053":"Voksenuddannelsescentre","1122":"\u00d8vrige MVU-institutioner","2022":"Centre for undervisningsmidler","1022":"Folkeh\u00f8jskoler","1011":"Efterskoler","1025":"Produktionsskoler","1021":"Dagh\u00f8jskoler","1071":"Erhvervsskoler m.v.","1081":"Maritime uddannelsesinstitutioner","1084":"Kunstneriske og kulturelle uddannelsesinstitutioner","1082":"Institutioner inden for politi, forsvar m.v.","1131":"Universiteter","1133":"Ph.d. skoler","1016":"Dagbehandlingstilbud og behandlingshjem","1072":"Private udbydere af AMU og EUD","1086":"Erhvervsakademier","1010":"Efterskoler med samlet s\u00e6rligt tilbud","1023":"Frie fagskoler","1085":"Professionsh\u00f8jskoler","1083":"Centre for offentlig kompetenceudvikling","1018":"Frie og private internationale skoler","9998":"Endnu ikke klassificerede institutioner","1017":"Kommunale internationale skoler"}